codegen/utils/__init__.py
codegen/utils/ai.py
codegen/utils/codebase_comparison_utils.py
codegen/utils/exception_handling.py
codegen/utils/exceptions.py
codegen/utils/json.py
codegen/utils/message_converting_utils.py
codegen/utils/perf_utils.py
codegen/utils/py.typed
codegen/utils/string_utils.py
codegen/utils/time_utils.py
codegen/utils/timeout_utils.py
codegen/utils/xml.py
codegen/utils/codemod/codemod_writer_decorators.py
codegen/utils/codeowners/__init__.py
codegen/utils/codeowners/utils.py
codegen/utils/file_io/create.py
codegen/utils/github_utils/config/constants.py
codegen/utils/github_utils/enums/diff_change_type.py
codegen_utils-6.6.6.dist-info/METADATA
codegen_utils-6.6.6.dist-info/WHEEL
codegen_utils-6.6.6.dist-info/RECORD
