Metadata-Version: 2.4
Name: codegen-utils
Version: 6.6.6
Summary: Codegen utils
License: 
Classifier: License :: OSI Approved :: Apache Software License
Requires-Python: >=3.9
Requires-Dist: pygithub==2.5.0
Requires-Dist: sentry-sdk==2.20.0
